MetaDR/EpCNN.py
MetaDR/WeighRF.py
MetaDR/__init__.py
MetaDR-3.0.0.dist-info/LICENSE.txt
MetaDR-3.0.0.dist-info/METADATA
MetaDR-3.0.0.dist-info/WHEEL
MetaDR-3.0.0.dist-info/top_level.txt
MetaDR-3.0.0.dist-info/RECORD
