Metadata-Version: 2.1
Name: MetaDR
Version: 3.0.0
Summary: MetaDR package
Home-page: https://github.com/Microbiods/MetaDR
Author: CHEN Xingjian
Author-email: xingjchen3-c@my.cityu.edu.hk
License: MIT License
Platform: all
Classifier: Intended Audience :: Developers
Classifier: Operating System :: OS Independent
Classifier: Natural Language :: Chinese (Simplified)
Classifier: Programming Language :: Python
Classifier: Programming Language :: Python :: 2
Classifier: Programming Language :: Python :: 2.7
Classifier: Programming Language :: Python :: 3
Classifier: Programming Language :: Python :: 3.5
Classifier: Programming Language :: Python :: 3.6
Classifier: Programming Language :: Python :: 3.7
Classifier: Programming Language :: Python :: 3.8
Classifier: Topic :: Software Development :: Libraries
Requires-Dist: xlrd (==1.2.0)
Requires-Dist: scipy (==1.7.1)
Requires-Dist: pandas (==1.3.2)
Requires-Dist: numpy (==1.19.5)
Requires-Dist: ete3 (==3.1.2)
Requires-Dist: tensorflow (==2.7.0)
Requires-Dist: scikit-learn (==0.24.2)
